gearscalculator/__init__.py
gearscalculator/definiciones.py
libreria_engranajes_marco-0.0.1.dist-info/METADATA
libreria_engranajes_marco-0.0.1.dist-info/WHEEL
libreria_engranajes_marco-0.0.1.dist-info/top_level.txt
libreria_engranajes_marco-0.0.1.dist-info/RECORD
