Metadata-Version: 2.4
Name: libreria_engranajes_marco
Version: 0.0.1
Summary: A simple library to calculate the diameters, numbers of teeth and size of stright gears
Author-email: Marco Enrique Rodriguez Hurtado <marco.rodriguez@ucb.edu.bo>
Classifier: Programming Language :: Python :: 3
Classifier: Operating System :: OS Independent
Requires-Python: >=3.9
